extmake/__init__.py
extmake/cache.py
extmake/cli.py
extmake/deps.py
extmake/dsn.py
extmake/git.py
extmake/parser.py
extmake/proxy.py
extmake/resolver.py
extmake-1.0.0.dist-info/LICENSE
extmake-1.0.0.dist-info/METADATA
extmake-1.0.0.dist-info/WHEEL
extmake-1.0.0.dist-info/entry_points.txt
extmake-1.0.0.dist-info/RECORD
