Metadata-Version: 2.1
Name: extmake
Version: 1.0.0
Summary: ExtMake - `make` wrapper with `include git=...` and more
Home-page: https://github.com/candidtim/extmake/
License: MIT
Keywords: make,wrapper,include,git,dependency
Author: candidtim
Author-email: timcandid@gmail.com
Requires-Python: >=3.10,<4.0
Classifier: Development Status :: 5 - Production/Stable
Classifier: Environment :: Console
Classifier: Intended Audience :: Developers
Classifier: License :: OSI Approved :: MIT License
Classifier: Operating System :: OS Independent
Classifier: Programming Language :: Python :: 3
Classifier: Programming Language :: Python :: 3.10
Classifier: Programming Language :: Python :: 3.11
Classifier: Programming Language :: Python :: 3.12
Classifier: Topic :: Software Development
Classifier: Topic :: Software Development :: Build Tools
Classifier: Topic :: Software Development :: Pre-processors
Requires-Dist: appdirs (>=1.4.4,<2.0.0)
Requires-Dist: click (>=8.1.7,<9.0.0)
Requires-Dist: requests (>=2.31.0,<3.0.0)
Project-URL: Bug Tracker, https://github.com/candidtim/extmake/issues
Project-URL: Documentation, https://github.com/candidtim/extmake/blob/master/README.md
Project-URL: Repository, https://github.com/candidtim/extmake/
